ddlk/__init__.py
ddlk/utils.py
ddlk/ddlk/__init__.py
ddlk/ddlk/cde.py
ddlk/ddlk/ddlk.py
ddlk/ddlk/gmm.py
ddlk/ddlk/mdn.py
ddlk/ddlk/swap.py
ddlk/testing/__init__.py
ddlk/testing/hrt.py
ddlk-0.0.0.2.dist-info/METADATA
ddlk-0.0.0.2.dist-info/WHEEL
ddlk-0.0.0.2.dist-info/top_level.txt
ddlk-0.0.0.2.dist-info/RECORD
