Metadata-Version: 2.1
Name: ddlk
Version: 0.0.0.2
Summary: Deep direct likelihood knockoffs
Home-page: https://github.com/rajesh-lab/ddlk
Author: Mukund Sudarshan
Author-email: ms7490+pip@nyu.edu
License: UNKNOWN
Platform: UNKNOWN
Classifier: Programming Language :: Python :: 3
Classifier: License :: OSI Approved :: GNU Affero General Public License v3
Classifier: Operating System :: OS Independent
Classifier: Topic :: Scientific/Engineering
Requires-Python: >=3.6
Requires-Dist: numpy (>=1.14.0)
Requires-Dist: matplotlib (>=2.0.0)
Requires-Dist: scipy (>=1.2.1)
Requires-Dist: scikit-learn (>=0.19.0)
Requires-Dist: tqdm (>=4.0.1)
Requires-Dist: torch (>=1.5.0)
Requires-Dist: torchvision (>=0.6.0)
Requires-Dist: pytorch-lightning (>=1.0.0)
